balderdash/__init__.py
balderdash/grafana.py
balderdash/kibana.py
balderdash-1.34.0.dist-info/LICENSE.txt
balderdash-1.34.0.dist-info/METADATA
balderdash-1.34.0.dist-info/WHEEL
balderdash-1.34.0.dist-info/top_level.txt
balderdash-1.34.0.dist-info/RECORD
