Metadata-Version: 2.1
Name: balderdash
Version: 1.34.0
Summary: Builders for monitoring dashboards
Home-page: http://github.com/daviddenton/balderdash/
Author: daviddenton
Author-email: denton.david+pypy@gmail.com
License: Apache 2.0
Platform: UNKNOWN
Classifier: Development Status :: 5 - Production/Stable
Classifier: Intended Audience :: Developers
Classifier: Natural Language :: English
Classifier: License :: OSI Approved :: Apache Software License
Classifier: Operating System :: OS Independent
Classifier: Programming Language :: Python
Classifier: Programming Language :: Python :: 2
Classifier: Programming Language :: Python :: 2.7
Classifier: Topic :: Software Development :: Libraries :: Python Modules
